lara_power_tools/__init__.py
lara_power_tools/appsync/__init__.py
lara_power_tools/appsync/auth.py
lara_power_tools/appsync/client.py
lara_power_tools/converters.py
lara_power_tools/dispatcher.py
lara_power_tools/formatters.py
lara_power_tools/opensearch.py
lara_power_tools/utils.py
lara_power_tools-0.6.0.dist-info/METADATA
lara_power_tools-0.6.0.dist-info/WHEEL
lara_power_tools-0.6.0.dist-info/RECORD
