Metadata-Version: 2.1
Name: lara-power-tools
Version: 0.6.0
Summary: 
Author: Engineering
Author-email: engineering@lara.health
Requires-Python: >=3.9,<4.0
Classifier: Programming Language :: Python :: 3
Classifier: Programming Language :: Python :: 3.9
Classifier: Programming Language :: Python :: 3.10
Classifier: Programming Language :: Python :: 3.11
Classifier: Programming Language :: Python :: 3.12
Requires-Dist: opensearch-py (>=2.8.0,<3.0.0)
Requires-Dist: pydantic (>=2.10.4,<3.0.0)
